[
  {
    "id": "76343f981d0bdaf7f428cfdfe9f5cbf6",
    "sport": "cbb",
    "home": "Bellarmine Knights",
    "away": "Jacksonville Dolphins",
    "commence": "2026-03-04T17:00:00Z",
    "spread_home": -2.5,
    "spread_away": 2.5,
    "total": 144.5,
    "ml_home": -170,
    "ml_away": 132,
    "spread_home_open": -1.5,
    "total_open": 147.5,
    "ml_home_open": -125,
    "ml_away_open": 104,
    "public_home_pct": 59,
    "public_away_pct": 41,
    "public_over_pct": 62,
    "public_under_pct": 38,
    "sharp_side": null,
    "sharp_total": "under",
    "steam_move": true,
    "rlm_side": false,
    "rlm_total": true,
    "snapshot_time": "2026-03-04T17:15:04.258Z",
    "snapshot_label": "12pm"
  },
  {
    "id": "3f8510356b010d6698c1ea8f75b736b1",
    "sport": "cbb",
    "home": "Florida Gulf Coast Eagles",
    "away": "North Alabama Lions",
    "commence": "2026-03-04T19:30:00Z",
    "spread_home": -7.5,
    "spread_away": 7.5,
    "total": 139.5,
    "ml_home": -375,
    "ml_away": 290,
    "spread_home_open": -6.5,
    "total_open": 142.5,
    "ml_home_open": -315,
    "ml_away_open": 250,
    "public_home_pct": 66,
    "public_away_pct": 34,
    "public_over_pct": 63,
    "public_under_pct": 37,
    "sharp_side": null,
    "sharp_total": "under",
    "steam_move": true,
    "rlm_side": false,
    "rlm_total": true,
    "snapshot_time": "2026-03-04T17:15:04.258Z",
    "snapshot_label": "12pm"
  },
  {
    "id": "53ad30f5ebd93132b1fcbb9573682771",
    "sport": "cbb",
    "home": "Eastern Kentucky Colonels",
    "away": "Stetson Hatters",
    "commence": "2026-03-04T22:00:00Z",
    "spread_home": -4.5,
    "spread_away": 4.5,
    "total": 155.5,
    "ml_home": -220,
    "ml_away": 180,
    "spread_home_open": -3.5,
    "total_open": 154.5,
    "ml_home_open": -205,
    "ml_away_open": 168,
    "public_home_pct": 62,
    "public_away_pct": 38,
    "public_over_pct": 56,
    "public_under_pct": 44,
    "sharp_side": null,
    "sharp_total": null,
    "steam_move": false,
    "rlm_side": false,
    "rlm_total": false,
    "snapshot_time": "2026-03-04T17:15:04.258Z",
    "snapshot_label": "12pm"
  },
  {
    "id": "6b8be6ad9cf80bcbf5ffd292fbfc9c18",
    "sport": "cbb",
    "home": "Butler Bulldogs",
    "away": "Creighton Bluejays",
    "commence": "2026-03-04T23:00:00Z",
    "spread_home": -2.5,
    "spread_away": 2.5,
    "total": 155.5,
    "ml_home": -148,
    "ml_away": 124,
    "spread_home_open": -2.5,
    "total_open": 155.5,
    "ml_home_open": -148,
    "ml_away_open": 124,
    "public_home_pct": 59,
    "public_away_pct": 41,
    "public_over_pct": 61,
    "public_under_pct": 39,
    "sharp_side": null,
    "sharp_total": null,
    "steam_move": false,
    "rlm_side": false,
    "rlm_total": false,
    "snapshot_time": "2026-03-04T17:15:04.258Z",
    "snapshot_label": "12pm"
  },
  {
    "id": "61164f56921094b6a3e70c83ba9b1a24",
    "sport": "cbb",
    "home": "James Madison Dukes",
    "away": "Louisiana Ragin' Cajuns",
    "commence": "2026-03-04T23:00:00Z",
    "spread_home": -6.5,
    "spread_away": 6.5,
    "total": 132.5,
    "ml_home": -270,
    "ml_away": 220,
    "spread_home_open": null,
    "total_open": null,
    "ml_home_open": null,
    "ml_away_open": null,
    "public_home_pct": 65,
    "public_away_pct": 35,
    "public_over_pct": 58,
    "public_under_pct": 42,
    "sharp_side": null,
    "sharp_total": null,
    "steam_move": false,
    "rlm_side": false,
    "rlm_total": false,
    "snapshot_time": "2026-03-04T17:15:04.258Z",
    "snapshot_label": "12pm"
  },
  {
    "id": "6047626b7a0aeafe4104c1a1573ba6dc",
    "sport": "cbb",
    "home": "La Salle Explorers",
    "away": "Fordham Rams",
    "commence": "2026-03-04T23:30:00Z",
    "spread_home": 2.5,
    "spread_away": -2.5,
    "total": 130.5,
    "ml_home": 115,
    "ml_away": -140,
    "spread_home_open": 2.5,
    "total_open": 134.5,
    "ml_home_open": 118,
    "ml_away_open": -145,
    "public_home_pct": 41,
    "public_away_pct": 59,
    "public_over_pct": 58,
    "public_under_pct": 42,
    "sharp_side": null,
    "sharp_total": "under",
    "steam_move": true,
    "rlm_side": false,
    "rlm_total": true,
    "snapshot_time": "2026-03-04T17:15:04.258Z",
    "snapshot_label": "12pm"
  },
  {
    "id": "676445c5e361c968ca7563af3e2f1971",
    "sport": "cbb",
    "home": "Indiana Hoosiers",
    "away": "Minnesota Golden Gophers",
    "commence": "2026-03-04T23:30:00Z",
    "spread_home": -6.5,
    "spread_away": 6.5,
    "total": 136.5,
    "ml_home": -305,
    "ml_away": 245,
    "spread_home_open": -7.5,
    "total_open": 138.5,
    "ml_home_open": -298,
    "ml_away_open": 240,
    "public_home_pct": 65,
    "public_away_pct": 35,
    "public_over_pct": 54,
    "public_under_pct": 46,
    "sharp_side": "away",
    "sharp_total": null,
    "steam_move": true,
    "rlm_side": true,
    "rlm_total": false,
    "snapshot_time": "2026-03-04T17:15:04.258Z",
    "snapshot_label": "12pm"
  },
  {
    "id": "ae96dcefbae84b5fea2f08283dcbd9eb",
    "sport": "cbb",
    "home": "Georgia Tech Yellow Jackets",
    "away": "California Golden Bears",
    "commence": "2026-03-05T00:00:00Z",
    "spread_home": 3.5,
    "spread_away": -3.5,
    "total": 155.5,
    "ml_home": 136,
    "ml_away": -162,
    "spread_home_open": 3.5,
    "total_open": 156.5,
    "ml_home_open": 140,
    "ml_away_open": -166,
    "public_home_pct": 40,
    "public_away_pct": 60,
    "public_over_pct": 60,
    "public_under_pct": 40,
    "sharp_side": null,
    "sharp_total": "under",
    "steam_move": false,
    "rlm_side": false,
    "rlm_total": true,
    "snapshot_time": "2026-03-04T17:15:04.258Z",
    "snapshot_label": "12pm"
  },
  {
    "id": "248a0b7e60d7976b31718c40b6b093e6",
    "sport": "cbb",
    "home": "Central Connecticut St Blue Devils",
    "away": "Wagner Seahawks",
    "commence": "2026-03-05T00:00:00Z",
    "spread_home": -5.5,
    "spread_away": 5.5,
    "total": 139.5,
    "ml_home": -225,
    "ml_away": 185,
    "spread_home_open": -4.5,
    "total_open": 139.5,
    "ml_home_open": -210,
    "ml_away_open": 170,
    "public_home_pct": 63,
    "public_away_pct": 37,
    "public_over_pct": 62,
    "public_under_pct": 38,
    "sharp_side": null,
    "sharp_total": null,
    "steam_move": false,
    "rlm_side": false,
    "rlm_total": false,
    "snapshot_time": "2026-03-04T17:15:04.258Z",
    "snapshot_label": "12pm"
  },
  {
    "id": "79d0877222e328b11f215f0b44bd33bb",
    "sport": "cbb",
    "home": "Charlotte 49ers",
    "away": "UAB Blazers",
    "commence": "2026-03-05T00:00:00Z",
    "spread_home": 1.5,
    "spread_away": -1.5,
    "total": 144.5,
    "ml_home": 100,
    "ml_away": -120,
    "spread_home_open": 1.5,
    "total_open": 144.5,
    "ml_home_open": 100,
    "ml_away_open": -120,
    "public_home_pct": 43,
    "public_away_pct": 57,
    "public_over_pct": 63,
    "public_under_pct": 37,
    "sharp_side": null,
    "sharp_total": null,
    "steam_move": false,
    "rlm_side": false,
    "rlm_total": false,
    "snapshot_time": "2026-03-04T17:15:04.258Z",
    "snapshot_label": "12pm"
  },
  {
    "id": "f9a0a489dcec91f49be7e1fe7148474e",
    "sport": "cbb",
    "home": "LIU Sharks",
    "away": "Chicago St Cougars",
    "commence": "2026-03-05T00:00:00Z",
    "spread_home": -11.5,
    "spread_away": 11.5,
    "total": 138.5,
    "ml_home": -800,
    "ml_away": 550,
    "spread_home_open": -11.5,
    "total_open": 138.5,
    "ml_home_open": -750,
    "ml_away_open": 525,
    "public_home_pct": 72,
    "public_away_pct": 28,
    "public_over_pct": 60,
    "public_under_pct": 40,
    "sharp_side": null,
    "sharp_total": null,
    "steam_move": false,
    "rlm_side": false,
    "rlm_total": false,
    "snapshot_time": "2026-03-04T17:15:04.258Z",
    "snapshot_label": "12pm"
  },
  {
    "id": "b312ad016d1672957f644672f27f162c",
    "sport": "cbb",
    "home": "Wright St Raiders",
    "away": "Cleveland St Vikings",
    "commence": "2026-03-05T00:00:00Z",
    "spread_home": -15.5,
    "spread_away": 15.5,
    "total": 161.5,
    "ml_home": -1600,
    "ml_away": 900,
    "spread_home_open": -13.5,
    "total_open": 161.5,
    "ml_home_open": -1100,
    "ml_away_open": 675,
    "public_home_pct": 75,
    "public_away_pct": 25,
    "public_over_pct": 55,
    "public_under_pct": 45,
    "sharp_side": null,
    "sharp_total": null,
    "steam_move": true,
    "rlm_side": false,
    "rlm_total": false,
    "snapshot_time": "2026-03-04T17:15:04.258Z",
    "snapshot_label": "12pm"
  },
  {
    "id": "cb43f07e738e9baa4e07a84e485c932c",
    "sport": "cbb",
    "home": "Davidson Wildcats",
    "away": "Saint Joseph's Hawks",
    "commence": "2026-03-05T00:00:00Z",
    "spread_home": -4.5,
    "spread_away": 4.5,
    "total": 136.5,
    "ml_home": -185,
    "ml_away": 154,
    "spread_home_open": -4.5,
    "total_open": 137.5,
    "ml_home_open": -190,
    "ml_away_open": 154,
    "public_home_pct": 62,
    "public_away_pct": 38,
    "public_over_pct": 56,
    "public_under_pct": 44,
    "sharp_side": null,
    "sharp_total": "under",
    "steam_move": false,
    "rlm_side": false,
    "rlm_total": true,
    "snapshot_time": "2026-03-04T17:15:04.258Z",
    "snapshot_label": "12pm"
  },
  {
    "id": "5eb52dbfb5a91bf99722f15e19a539f9",
    "sport": "cbb",
    "home": "Detroit Mercy Titans",
    "away": "Milwaukee Panthers",
    "commence": "2026-03-05T00:00:00Z",
    "spread_home": -1.5,
    "spread_away": 1.5,
    "total": 151.5,
    "ml_home": -142,
    "ml_away": 120,
    "spread_home_open": -2.5,
    "total_open": 153.5,
    "ml_home_open": -148,
    "ml_away_open": 124,
    "public_home_pct": 57,
    "public_away_pct": 43,
    "public_over_pct": 54,
    "public_under_pct": 46,
    "sharp_side": "away",
    "sharp_total": null,
    "steam_move": true,
    "rlm_side": true,
    "rlm_total": false,
    "snapshot_time": "2026-03-04T17:15:04.258Z",
    "snapshot_label": "12pm"
  },
  {
    "id": "421aeceda1a381818cde0661d79e095b",
    "sport": "cbb",
    "home": "Rhode Island Rams",
    "away": "Duquesne Dukes",
    "commence": "2026-03-05T00:00:00Z",
    "spread_home": -2.5,
    "spread_away": 2.5,
    "total": 143.5,
    "ml_home": -130,
    "ml_away": 110,
    "spread_home_open": -1.5,
    "total_open": 143.5,
    "ml_home_open": -120,
    "ml_away_open": 100,
    "public_home_pct": 59,
    "public_away_pct": 41,
    "public_over_pct": 65,
    "public_under_pct": 35,
    "sharp_side": null,
    "sharp_total": null,
    "steam_move": false,
    "rlm_side": false,
    "rlm_total": false,
    "snapshot_time": "2026-03-04T17:15:04.258Z",
    "snapshot_label": "12pm"
  },
  {
    "id": "724a4b43049e413000d28b01c5d6d555",
    "sport": "cbb",
    "home": "SIU-Edwardsville Cougars",
    "away": "Eastern Illinois Panthers",
    "commence": "2026-03-05T00:00:00Z",
    "spread_home": -4.5,
    "spread_away": 4.5,
    "total": 126.5,
    "ml_home": -225,
    "ml_away": 185,
    "spread_home_open": -5.5,
    "total_open": 127.5,
    "ml_home_open": -250,
    "ml_away_open": 205,
    "public_home_pct": 62,
    "public_away_pct": 38,
    "public_over_pct": 65,
    "public_under_pct": 35,
    "sharp_side": "away",
    "sharp_total": "under",
    "steam_move": false,
    "rlm_side": true,
    "rlm_total": true,
    "snapshot_time": "2026-03-04T17:15:04.258Z",
    "snapshot_label": "12pm"
  },
  {
    "id": "5e9fb33e565e4dec0e454876b15ff913",
    "sport": "cbb",
    "home": "Mercyhurst Lakers",
    "away": "Fairleigh Dickinson Knights",
    "commence": "2026-03-05T00:00:00Z",
    "spread_home": -4.5,
    "spread_away": 4.5,
    "total": 132.5,
    "ml_home": -205,
    "ml_away": 170,
    "spread_home_open": -4.5,
    "total_open": 134.5,
    "ml_home_open": -192,
    "ml_away_open": 160,
    "public_home_pct": 62,
    "public_away_pct": 38,
    "public_over_pct": 57,
    "public_under_pct": 43,
    "sharp_side": null,
    "sharp_total": "under",
    "steam_move": true,
    "rlm_side": false,
    "rlm_total": true,
    "snapshot_time": "2026-03-04T17:15:04.258Z",
    "snapshot_label": "12pm"
  },
  {
    "id": "ac2cf3cc1c56249589b2da6adbb080ac",
    "sport": "cbb",
    "home": "GW Revolutionaries",
    "away": "St. Bonaventure Bonnies",
    "commence": "2026-03-05T00:00:00Z",
    "spread_home": -9.5,
    "spread_away": 9.5,
    "total": 157.5,
    "ml_home": -475,
    "ml_away": 360,
    "spread_home_open": -9.5,
    "total_open": 157.5,
    "ml_home_open": -375,
    "ml_away_open": 300,
    "public_home_pct": 69,
    "public_away_pct": 31,
    "public_over_pct": 62,
    "public_under_pct": 38,
    "sharp_side": null,
    "sharp_total": null,
    "steam_move": false,
    "rlm_side": false,
    "rlm_total": false,
    "snapshot_time": "2026-03-04T17:15:04.258Z",
    "snapshot_label": "12pm"
  },
  {
    "id": "8939a2fa5c65a6a357114557ba2ff6b4",
    "sport": "cbb",
    "home": "Le Moyne Dolphins",
    "away": "Stonehill Skyhawks",
    "commence": "2026-03-05T00:00:00Z",
    "spread_home": -6.5,
    "spread_away": 6.5,
    "total": 136.5,
    "ml_home": -275,
    "ml_away": 220,
    "spread_home_open": -6.5,
    "total_open": 134.5,
    "ml_home_open": -275,
    "ml_away_open": 220,
    "public_home_pct": 65,
    "public_away_pct": 35,
    "public_over_pct": 62,
    "public_under_pct": 38,
    "sharp_side": null,
    "sharp_total": null,
    "steam_move": true,
    "rlm_side": false,
    "rlm_total": false,
    "snapshot_time": "2026-03-04T17:15:04.258Z",
    "snapshot_label": "12pm"
  },
  {
    "id": "3b8315764ce0a11613f19bac50311d72",
    "sport": "cbb",
    "home": "Providence Friars",
    "away": "Marquette Golden Eagles",
    "commence": "2026-03-05T00:00:00Z",
    "spread_home": -5.5,
    "spread_away": 5.5,
    "total": 161.5,
    "ml_home": -218,
    "ml_away": 180,
    "spread_home_open": -3.5,
    "total_open": 161.5,
    "ml_home_open": -192,
    "ml_away_open": 160,
    "public_home_pct": 63,
    "public_away_pct": 37,
    "public_over_pct": 58,
    "public_under_pct": 42,
    "sharp_side": null,
    "sharp_total": null,
    "steam_move": true,
    "rlm_side": false,
    "rlm_total": false,
    "snapshot_time": "2026-03-04T17:15:04.258Z",
    "snapshot_label": "12pm"
  },
  {
    "id": "989c39d7bfb059e969a377726ce3190f",
    "sport": "cbb",
    "home": "Oakland Golden Grizzlies",
    "away": "Northern Kentucky Norse",
    "commence": "2026-03-05T00:00:00Z",
    "spread_home": -2.5,
    "spread_away": 2.5,
    "total": 160.5,
    "ml_home": -148,
    "ml_away": 124,
    "spread_home_open": -2.5,
    "total_open": 158.5,
    "ml_home_open": -135,
    "ml_away_open": 114,
    "public_home_pct": 59,
    "public_away_pct": 41,
    "public_over_pct": 55,
    "public_under_pct": 45,
    "sharp_side": null,
    "sharp_total": null,
    "steam_move": true,
    "rlm_side": false,
    "rlm_total": false,
    "snapshot_time": "2026-03-04T17:15:04.258Z",
    "snapshot_label": "12pm"
  },
  {
    "id": "645accaafa070c9c4c797f4b61a62a7a",
    "sport": "cbb",
    "home": "Robert Morris Colonials",
    "away": "Youngstown St Penguins",
    "commence": "2026-03-05T00:00:00Z",
    "spread_home": -4.5,
    "spread_away": 4.5,
    "total": 141.5,
    "ml_home": -205,
    "ml_away": 170,
    "spread_home_open": -4.5,
    "total_open": 142.5,
    "ml_home_open": -192,
    "ml_away_open": 160,
    "public_home_pct": 62,
    "public_away_pct": 38,
    "public_over_pct": 64,
    "public_under_pct": 36,
    "sharp_side": null,
    "sharp_total": "under",
    "steam_move": false,
    "rlm_side": false,
    "rlm_total": true,
    "snapshot_time": "2026-03-04T17:15:04.258Z",
    "snapshot_label": "12pm"
  },
  {
    "id": "77ae3e245b749b6f425f671b7dc30d15",
    "sport": "cbb",
    "home": "Arkansas Razorbacks",
    "away": "Texas Longhorns",
    "commence": "2026-03-05T00:00:07Z",
    "spread_home": -7.5,
    "spread_away": 7.5,
    "total": 164.5,
    "ml_home": -345,
    "ml_away": 265,
    "spread_home_open": -7.5,
    "total_open": 165.5,
    "ml_home_open": -375,
    "ml_away_open": 290,
    "public_home_pct": 66,
    "public_away_pct": 34,
    "public_over_pct": 56,
    "public_under_pct": 44,
    "sharp_side": null,
    "sharp_total": "under",
    "steam_move": false,
    "rlm_side": false,
    "rlm_total": true,
    "snapshot_time": "2026-03-04T17:15:04.258Z",
    "snapshot_label": "12pm"
  },
  {
    "id": "ae77fa9cd25c609e9c799f17aff1fc81",
    "sport": "cbb",
    "home": "SMU Mustangs",
    "away": "Miami Hurricanes",
    "commence": "2026-03-05T00:00:09Z",
    "spread_home": -1.5,
    "spread_away": 1.5,
    "total": 160.5,
    "ml_home": -137,
    "ml_away": 114,
    "spread_home_open": -1.5,
    "total_open": 160.5,
    "ml_home_open": -122,
    "ml_away_open": 102,
    "public_home_pct": 57,
    "public_away_pct": 43,
    "public_over_pct": 65,
    "public_under_pct": 35,
    "sharp_side": null,
    "sharp_total": null,
    "steam_move": false,
    "rlm_side": false,
    "rlm_total": false,
    "snapshot_time": "2026-03-04T17:15:04.258Z",
    "snapshot_label": "12pm"
  },
  {
    "id": "77205f60188120987dc6c6a44e53db3b",
    "sport": "cbb",
    "home": "South Carolina Upstate Spartans",
    "away": "Gardner-Webb Bulldogs",
    "commence": "2026-03-05T00:30:00Z",
    "spread_home": -11.5,
    "spread_away": 11.5,
    "total": 145.5,
    "ml_home": -800,
    "ml_away": 550,
    "spread_home_open": -10.5,
    "total_open": 148.5,
    "ml_home_open": -500,
    "ml_away_open": 375,
    "public_home_pct": 72,
    "public_away_pct": 28,
    "public_over_pct": 56,
    "public_under_pct": 44,
    "sharp_side": null,
    "sharp_total": "under",
    "steam_move": true,
    "rlm_side": false,
    "rlm_total": true,
    "snapshot_time": "2026-03-04T17:15:04.258Z",
    "snapshot_label": "12pm"
  },
  {
    "id": "5386f0f5dfb5e33ddb39d9ace1ab95e1",
    "sport": "cbb",
    "home": "West Georgia Wolves",
    "away": "North Florida Ospreys",
    "commence": "2026-03-05T00:30:00Z",
    "spread_home": -2.5,
    "spread_away": 2.5,
    "total": 158.5,
    "ml_home": -162,
    "ml_away": 136,
    "spread_home_open": -3.5,
    "total_open": 157.5,
    "ml_home_open": -170,
    "ml_away_open": 140,
    "public_home_pct": 59,
    "public_away_pct": 41,
    "public_over_pct": 64,
    "public_under_pct": 36,
    "sharp_side": "away",
    "sharp_total": null,
    "steam_move": false,
    "rlm_side": true,
    "rlm_total": false,
    "snapshot_time": "2026-03-04T17:15:04.258Z",
    "snapshot_label": "12pm"
  },
  {
    "id": "900965482d00c60d4b09722d74034510",
    "sport": "cbb",
    "home": "Penn State Nittany Lions",
    "away": "Ohio State Buckeyes",
    "commence": "2026-03-05T00:30:00Z",
    "spread_home": 6.5,
    "spread_away": -6.5,
    "total": 152.5,
    "ml_home": 240,
    "ml_away": -298,
    "spread_home_open": 7.5,
    "total_open": 153.5,
    "ml_home_open": 270,
    "ml_away_open": -340,
    "public_home_pct": 35,
    "public_away_pct": 65,
    "public_over_pct": 53,
    "public_under_pct": 47,
    "sharp_side": "home",
    "sharp_total": null,
    "steam_move": false,
    "rlm_side": true,
    "rlm_total": false,
    "snapshot_time": "2026-03-04T17:15:04.258Z",
    "snapshot_label": "12pm"
  },
  {
    "id": "90f99c056c76aaff829583f20825127b",
    "sport": "cbb",
    "home": "DePaul Blue Demons",
    "away": "Villanova Wildcats",
    "commence": "2026-03-05T01:00:00Z",
    "spread_home": 2.5,
    "spread_away": -2.5,
    "total": 135.5,
    "ml_home": 124,
    "ml_away": -148,
    "spread_home_open": 3.5,
    "total_open": 135.5,
    "ml_home_open": 136,
    "ml_away_open": -162,
    "public_home_pct": 41,
    "public_away_pct": 59,
    "public_over_pct": 62,
    "public_under_pct": 38,
    "sharp_side": "home",
    "sharp_total": null,
    "steam_move": false,
    "rlm_side": true,
    "rlm_total": false,
    "snapshot_time": "2026-03-04T17:15:04.258Z",
    "snapshot_label": "12pm"
  },
  {
    "id": "c9892993fb81b6238aa7fa7d547a974f",
    "sport": "cbb",
    "home": "Saint Louis Billikens",
    "away": "Loyola (Chi) Ramblers",
    "commence": "2026-03-05T01:00:00Z",
    "spread_home": -22.5,
    "spread_away": 22.5,
    "total": 155.5,
    "ml_home": -8000,
    "ml_away": 2200,
    "spread_home_open": -24.5,
    "total_open": 155.5,
    "ml_home_open": null,
    "ml_away_open": null,
    "public_home_pct": 75,
    "public_away_pct": 25,
    "public_over_pct": 56,
    "public_under_pct": 44,
    "sharp_side": "away",
    "sharp_total": null,
    "steam_move": true,
    "rlm_side": true,
    "rlm_total": false,
    "snapshot_time": "2026-03-04T17:15:04.258Z",
    "snapshot_label": "12pm"
  },
  {
    "id": "48fa3a7a7fd73baf01685922d426f176",
    "sport": "cbb",
    "home": "Wisconsin Badgers",
    "away": "Maryland Terrapins",
    "commence": "2026-03-05T01:00:00Z",
    "spread_home": -14.5,
    "spread_away": 14.5,
    "total": 154.5,
    "ml_home": -1350,
    "ml_away": 800,
    "spread_home_open": -13.5,
    "total_open": 153.5,
    "ml_home_open": -1100,
    "ml_away_open": 700,
    "public_home_pct": 75,
    "public_away_pct": 25,
    "public_over_pct": 60,
    "public_under_pct": 40,
    "sharp_side": null,
    "sharp_total": null,
    "steam_move": false,
    "rlm_side": false,
    "rlm_total": false,
    "snapshot_time": "2026-03-04T17:15:04.258Z",
    "snapshot_label": "12pm"
  },
  {
    "id": "25035ada3daf938790fa8afcd155f367",
    "sport": "cbb",
    "home": "North Texas Mean Green",
    "away": "Rice Owls",
    "commence": "2026-03-05T01:00:00Z",
    "spread_home": -7.5,
    "spread_away": 7.5,
    "total": 137.5,
    "ml_home": -340,
    "ml_away": 270,
    "spread_home_open": -7.5,
    "total_open": 140.5,
    "ml_home_open": -340,
    "ml_away_open": 270,
    "public_home_pct": 66,
    "public_away_pct": 34,
    "public_over_pct": 63,
    "public_under_pct": 37,
    "sharp_side": null,
    "sharp_total": "under",
    "steam_move": true,
    "rlm_side": false,
    "rlm_total": true,
    "snapshot_time": "2026-03-04T17:15:04.258Z",
    "snapshot_label": "12pm"
  },
  {
    "id": "9f2ade8ad19e3e9ea4bb20b92fa34458",
    "sport": "cbb",
    "home": "Oral Roberts Golden Eagles",
    "away": "UMKC Kangaroos",
    "commence": "2026-03-05T01:00:00Z",
    "spread_home": -8.5,
    "spread_away": 8.5,
    "total": 147.5,
    "ml_home": -425,
    "ml_away": 330,
    "spread_home_open": -8.5,
    "total_open": 147.5,
    "ml_home_open": -345,
    "ml_away_open": 275,
    "public_home_pct": 68,
    "public_away_pct": 32,
    "public_over_pct": 55,
    "public_under_pct": 45,
    "sharp_side": null,
    "sharp_total": null,
    "steam_move": false,
    "rlm_side": false,
    "rlm_total": false,
    "snapshot_time": "2026-03-04T17:15:04.258Z",
    "snapshot_label": "12pm"
  },
  {
    "id": "d000ae211a3dc8789a01042034a6d874",
    "sport": "cbb",
    "home": "Georgia Southern Eagles",
    "away": "Old Dominion Monarchs",
    "commence": "2026-03-05T01:30:00Z",
    "spread_home": -2.5,
    "spread_away": 2.5,
    "total": 158.5,
    "ml_home": -135,
    "ml_away": 114,
    "spread_home_open": null,
    "total_open": null,
    "ml_home_open": null,
    "ml_away_open": null,
    "public_home_pct": 59,
    "public_away_pct": 41,
    "public_over_pct": 53,
    "public_under_pct": 47,
    "sharp_side": null,
    "sharp_total": null,
    "steam_move": false,
    "rlm_side": false,
    "rlm_total": false,
    "snapshot_time": "2026-03-04T17:15:04.258Z",
    "snapshot_label": "12pm"
  },
  {
    "id": "b51aa48139345bae549e8f5b8c2e707c",
    "sport": "cbb",
    "home": "Northwestern Wildcats",
    "away": "Purdue Boilermakers",
    "commence": "2026-03-05T01:30:00Z",
    "spread_home": 11.5,
    "spread_away": -11.5,
    "total": 146.5,
    "ml_home": 380,
    "ml_away": -500,
    "spread_home_open": 11.5,
    "total_open": 147.5,
    "ml_home_open": 360,
    "ml_away_open": -470,
    "public_home_pct": 28,
    "public_away_pct": 72,
    "public_over_pct": 62,
    "public_under_pct": 38,
    "sharp_side": null,
    "sharp_total": "under",
    "steam_move": false,
    "rlm_side": false,
    "rlm_total": true,
    "snapshot_time": "2026-03-04T17:15:04.258Z",
    "snapshot_label": "12pm"
  },
  {
    "id": "40df21960dec1c660fae9256810c7405",
    "sport": "cbb",
    "home": "Houston Cougars",
    "away": "Baylor Bears",
    "commence": "2026-03-05T02:00:00Z",
    "spread_home": -15.5,
    "spread_away": 15.5,
    "total": 141.5,
    "ml_home": -1650,
    "ml_away": 950,
    "spread_home_open": -14.5,
    "total_open": 141.5,
    "ml_home_open": -2100,
    "ml_away_open": 1100,
    "public_home_pct": 75,
    "public_away_pct": 25,
    "public_over_pct": 55,
    "public_under_pct": 45,
    "sharp_side": null,
    "sharp_total": null,
    "steam_move": false,
    "rlm_side": false,
    "rlm_total": false,
    "snapshot_time": "2026-03-04T17:15:04.258Z",
    "snapshot_label": "12pm"
  },
  {
    "id": "9fdae0a051acec61f4d841876c8af6b4",
    "sport": "cbb",
    "home": "Pittsburgh Panthers",
    "away": "Florida St Seminoles",
    "commence": "2026-03-05T02:00:00Z",
    "spread_home": 2.5,
    "spread_away": -2.5,
    "total": 143.5,
    "ml_home": 124,
    "ml_away": -148,
    "spread_home_open": 1.5,
    "total_open": 145.5,
    "ml_home_open": 100,
    "ml_away_open": -120,
    "public_home_pct": 41,
    "public_away_pct": 59,
    "public_over_pct": 56,
    "public_under_pct": 44,
    "sharp_side": null,
    "sharp_total": "under",
    "steam_move": true,
    "rlm_side": false,
    "rlm_total": true,
    "snapshot_time": "2026-03-04T17:15:04.258Z",
    "snapshot_label": "12pm"
  },
  {
    "id": "c98fc48a731f7219dc01386b5d4598aa",
    "sport": "cbb",
    "home": "Notre Dame Fighting Irish",
    "away": "Stanford Cardinal",
    "commence": "2026-03-05T02:00:00Z",
    "spread_home": 1.5,
    "spread_away": -1.5,
    "total": 145.5,
    "ml_home": -102,
    "ml_away": -118,
    "spread_home_open": -1.5,
    "total_open": 145.5,
    "ml_home_open": -120,
    "ml_away_open": 100,
    "public_home_pct": 43,
    "public_away_pct": 57,
    "public_over_pct": 63,
    "public_under_pct": 37,
    "sharp_side": null,
    "sharp_total": null,
    "steam_move": true,
    "rlm_side": false,
    "rlm_total": false,
    "snapshot_time": "2026-03-04T17:15:04.258Z",
    "snapshot_label": "12pm"
  },
  {
    "id": "ca0226079e332bb70aee624f355715c6",
    "sport": "cbb",
    "home": "Lindenwood Lions",
    "away": "Arkansas-Little Rock Trojans",
    "commence": "2026-03-05T02:30:00Z",
    "spread_home": -2.5,
    "spread_away": 2.5,
    "total": 148.5,
    "ml_home": -142,
    "ml_away": 120,
    "spread_home_open": -3.5,
    "total_open": 148.5,
    "ml_home_open": -155,
    "ml_away_open": 125,
    "public_home_pct": 59,
    "public_away_pct": 41,
    "public_over_pct": 63,
    "public_under_pct": 37,
    "sharp_side": "away",
    "sharp_total": null,
    "steam_move": false,
    "rlm_side": true,
    "rlm_total": false,
    "snapshot_time": "2026-03-04T17:15:04.258Z",
    "snapshot_label": "12pm"
  },
  {
    "id": "562f0f395633cac0b40b104fededab77",
    "sport": "cbb",
    "home": "New Mexico Lobos",
    "away": "Colorado St Rams",
    "commence": "2026-03-05T03:00:00Z",
    "spread_home": -8.5,
    "spread_away": 8.5,
    "total": 150.5,
    "ml_home": -425,
    "ml_away": 330,
    "spread_home_open": -8.5,
    "total_open": 149.5,
    "ml_home_open": -355,
    "ml_away_open": 280,
    "public_home_pct": 68,
    "public_away_pct": 32,
    "public_over_pct": 56,
    "public_under_pct": 44,
    "sharp_side": null,
    "sharp_total": null,
    "steam_move": false,
    "rlm_side": false,
    "rlm_total": false,
    "snapshot_time": "2026-03-04T17:15:04.258Z",
    "snapshot_label": "12pm"
  },
  {
    "id": "2c709e184eb38007d2f96e0bf131d1c2",
    "sport": "cbb",
    "home": "Washington Huskies",
    "away": "USC Trojans",
    "commence": "2026-03-05T03:30:00Z",
    "spread_home": -6.5,
    "spread_away": 6.5,
    "total": 150.5,
    "ml_home": -265,
    "ml_away": 215,
    "spread_home_open": -6.5,
    "total_open": 151.5,
    "ml_home_open": -278,
    "ml_away_open": 225,
    "public_home_pct": 65,
    "public_away_pct": 35,
    "public_over_pct": 64,
    "public_under_pct": 36,
    "sharp_side": null,
    "sharp_total": "under",
    "steam_move": false,
    "rlm_side": false,
    "rlm_total": true,
    "snapshot_time": "2026-03-04T17:15:04.258Z",
    "snapshot_label": "12pm"
  },
  {
    "id": "a448dfd10bf5215735e63896d4a80ca9",
    "sport": "cbb",
    "home": "Ohio Bobcats",
    "away": "Miami (OH) RedHawks",
    "commence": "2026-03-07T02:00:00Z",
    "spread_home": 5.5,
    "spread_away": -5.5,
    "total": 158.5,
    "ml_home": 230,
    "ml_away": -285,
    "spread_home_open": null,
    "total_open": null,
    "ml_home_open": null,
    "ml_away_open": null,
    "public_home_pct": 37,
    "public_away_pct": 63,
    "public_over_pct": 58,
    "public_under_pct": 42,
    "sharp_side": null,
    "sharp_total": null,
    "steam_move": false,
    "rlm_side": false,
    "rlm_total": false,
    "snapshot_time": "2026-03-04T17:15:04.258Z",
    "snapshot_label": "12pm"
  }
]