[
  {
    "id": "a75f0e1a856bd60f28f5b0c57fc99270",
    "sport": "nhl",
    "home": "Winnipeg Jets",
    "away": "St Louis Blues",
    "commence": "2026-03-15T19:10:00Z",
    "spread_home": -1.5,
    "spread_away": 1.5,
    "total": 5.5,
    "ml_home": -115,
    "ml_away": -105,
    "spread_home_open": -1.5,
    "total_open": 5.5,
    "ml_home_open": -125,
    "ml_away_open": 105,
    "public_home_pct": 57,
    "public_away_pct": 43,
    "public_over_pct": 60,
    "public_under_pct": 40,
    "sharp_side": null,
    "sharp_total": null,
    "steam_move": false,
    "rlm_side": false,
    "rlm_total": false,
    "snapshot_time": "2026-03-15T16:15:03.677Z",
    "snapshot_label": "12pm"
  },
  {
    "id": "86375ff5a0a406f1f278039808088533",
    "sport": "nhl",
    "home": "Ottawa Senators",
    "away": "San Jose Sharks",
    "commence": "2026-03-15T21:10:00Z",
    "spread_home": -1.5,
    "spread_away": 1.5,
    "total": 6.5,
    "ml_home": -205,
    "ml_away": 170,
    "spread_home_open": -1.5,
    "total_open": 6.5,
    "ml_home_open": -218,
    "ml_away_open": 180,
    "public_home_pct": 57,
    "public_away_pct": 43,
    "public_over_pct": 55,
    "public_under_pct": 45,
    "sharp_side": null,
    "sharp_total": null,
    "steam_move": false,
    "rlm_side": false,
    "rlm_total": false,
    "snapshot_time": "2026-03-15T16:15:03.677Z",
    "snapshot_label": "12pm"
  },
  {
    "id": "7031b580a7cc254a4070f290e0cb2e4a",
    "sport": "nhl",
    "home": "Montréal Canadiens",
    "away": "Anaheim Ducks",
    "commence": "2026-03-15T23:10:00Z",
    "spread_home": -1.5,
    "spread_away": 1.5,
    "total": 6.5,
    "ml_home": -148,
    "ml_away": 124,
    "spread_home_open": -1.5,
    "total_open": 6.5,
    "ml_home_open": -148,
    "ml_away_open": 124,
    "public_home_pct": 57,
    "public_away_pct": 43,
    "public_over_pct": 64,
    "public_under_pct": 36,
    "sharp_side": null,
    "sharp_total": null,
    "steam_move": false,
    "rlm_side": false,
    "rlm_total": false,
    "snapshot_time": "2026-03-15T16:15:03.677Z",
    "snapshot_label": "12pm"
  },
  {
    "id": "a4e162193979f1f5f466d64f91fb59f4",
    "sport": "nhl",
    "home": "Minnesota Wild",
    "away": "Toronto Maple Leafs",
    "commence": "2026-03-15T23:40:00Z",
    "spread_home": -1.5,
    "spread_away": 1.5,
    "total": 6.5,
    "ml_home": -250,
    "ml_away": 205,
    "spread_home_open": -1.5,
    "total_open": 6.5,
    "ml_home_open": -250,
    "ml_away_open": 205,
    "public_home_pct": 57,
    "public_away_pct": 43,
    "public_over_pct": 55,
    "public_under_pct": 45,
    "sharp_side": null,
    "sharp_total": null,
    "steam_move": false,
    "rlm_side": false,
    "rlm_total": false,
    "snapshot_time": "2026-03-15T16:15:03.677Z",
    "snapshot_label": "12pm"
  },
  {
    "id": "5f08ff7521f7518d54f7690fbcec1d38",
    "sport": "nhl",
    "home": "Edmonton Oilers",
    "away": "Nashville Predators",
    "commence": "2026-03-16T00:10:00Z",
    "spread_home": -1.5,
    "spread_away": 1.5,
    "total": 6.5,
    "ml_home": -185,
    "ml_away": 154,
    "spread_home_open": -1.5,
    "total_open": 6.5,
    "ml_home_open": -185,
    "ml_away_open": 154,
    "public_home_pct": 57,
    "public_away_pct": 43,
    "public_over_pct": 62,
    "public_under_pct": 38,
    "sharp_side": null,
    "sharp_total": null,
    "steam_move": false,
    "rlm_side": false,
    "rlm_total": false,
    "snapshot_time": "2026-03-15T16:15:03.677Z",
    "snapshot_label": "12pm"
  },
  {
    "id": "3e60bb8c3aaf40bb02f8ec3fe3db9abd",
    "sport": "nhl",
    "home": "Seattle Kraken",
    "away": "Florida Panthers",
    "commence": "2026-03-16T00:10:00Z",
    "spread_home": 1.5,
    "spread_away": -1.5,
    "total": 5.5,
    "ml_home": 110,
    "ml_away": -130,
    "spread_home_open": 1.5,
    "total_open": 6.5,
    "ml_home_open": 110,
    "ml_away_open": -130,
    "public_home_pct": 43,
    "public_away_pct": 57,
    "public_over_pct": 60,
    "public_under_pct": 40,
    "sharp_side": null,
    "sharp_total": "under",
    "steam_move": false,
    "rlm_side": false,
    "rlm_total": true,
    "snapshot_time": "2026-03-15T16:15:03.677Z",
    "snapshot_label": "12pm"
  },
  {
    "id": "a5511fee3fcd590001e5e72ee1a4606b",
    "sport": "nhl",
    "home": "New Jersey Devils",
    "away": "Boston Bruins",
    "commence": "2026-03-16T23:00:00Z",
    "spread_home": -1.5,
    "spread_away": 1.5,
    "total": 6.5,
    "ml_home": -118,
    "ml_away": -102,
    "spread_home_open": null,
    "total_open": null,
    "ml_home_open": null,
    "ml_away_open": null,
    "public_home_pct": 57,
    "public_away_pct": 43,
    "public_over_pct": 56,
    "public_under_pct": 44,
    "sharp_side": null,
    "sharp_total": null,
    "steam_move": false,
    "rlm_side": false,
    "rlm_total": false,
    "snapshot_time": "2026-03-15T16:15:03.677Z",
    "snapshot_label": "12pm"
  },
  {
    "id": "4210d1bdce81a6c73f692336bb97d42a",
    "sport": "nhl",
    "home": "Detroit Red Wings",
    "away": "Calgary Flames",
    "commence": "2026-03-16T23:00:00Z",
    "spread_home": -1.5,
    "spread_away": 1.5,
    "total": 5.5,
    "ml_home": -180,
    "ml_away": 150,
    "spread_home_open": null,
    "total_open": null,
    "ml_home_open": null,
    "ml_away_open": null,
    "public_home_pct": 57,
    "public_away_pct": 43,
    "public_over_pct": 59,
    "public_under_pct": 41,
    "sharp_side": null,
    "sharp_total": null,
    "steam_move": false,
    "rlm_side": false,
    "rlm_total": false,
    "snapshot_time": "2026-03-15T16:15:03.677Z",
    "snapshot_label": "12pm"
  },
  {
    "id": "0e274047f6a166b5b3aa6fb05edffe30",
    "sport": "nhl",
    "home": "New York Rangers",
    "away": "Los Angeles Kings",
    "commence": "2026-03-16T23:00:00Z",
    "spread_home": 1.5,
    "spread_away": -1.5,
    "total": 5.5,
    "ml_home": 105,
    "ml_away": -126,
    "spread_home_open": null,
    "total_open": null,
    "ml_home_open": null,
    "ml_away_open": null,
    "public_home_pct": 43,
    "public_away_pct": 57,
    "public_over_pct": 63,
    "public_under_pct": 37,
    "sharp_side": null,
    "sharp_total": null,
    "steam_move": false,
    "rlm_side": false,
    "rlm_total": false,
    "snapshot_time": "2026-03-15T16:15:03.677Z",
    "snapshot_label": "12pm"
  },
  {
    "id": "095f4a82a3fef717e6d0e5e66f81fdd5",
    "sport": "nhl",
    "home": "Dallas Stars",
    "away": "Utah Mammoth",
    "commence": "2026-03-17T00:00:00Z",
    "spread_home": -1.5,
    "spread_away": 1.5,
    "total": 5.5,
    "ml_home": -156,
    "ml_away": 130,
    "spread_home_open": null,
    "total_open": null,
    "ml_home_open": null,
    "ml_away_open": null,
    "public_home_pct": 57,
    "public_away_pct": 43,
    "public_over_pct": 61,
    "public_under_pct": 39,
    "sharp_side": null,
    "sharp_total": null,
    "steam_move": false,
    "rlm_side": false,
    "rlm_total": false,
    "snapshot_time": "2026-03-15T16:15:03.677Z",
    "snapshot_label": "12pm"
  },
  {
    "id": "87e2100553dcf91e4333415ec629a8a8",
    "sport": "nhl",
    "home": "Colorado Avalanche",
    "away": "Pittsburgh Penguins",
    "commence": "2026-03-17T01:30:00Z",
    "spread_home": -1.5,
    "spread_away": 1.5,
    "total": 6.5,
    "ml_home": -245,
    "ml_away": 198,
    "spread_home_open": null,
    "total_open": null,
    "ml_home_open": null,
    "ml_away_open": null,
    "public_home_pct": 57,
    "public_away_pct": 43,
    "public_over_pct": 61,
    "public_under_pct": 39,
    "sharp_side": null,
    "sharp_total": null,
    "steam_move": false,
    "rlm_side": false,
    "rlm_total": false,
    "snapshot_time": "2026-03-15T16:15:03.677Z",
    "snapshot_label": "12pm"
  }
]